b3j0f/__init__.py
b3j0f/sync/version.py
b3j0f/sync/access.py
b3j0f/sync/__init__.py
b3j0f/sync/core.py
b3j0f/sync/store.py
b3j0f/sync/model.py
b3j0f/sync/test/access.py
b3j0f/sync/test/__init__.py
b3j0f/sync/test/core.py
b3j0f/sync/test/store.py
b3j0f/sync/test/model.py
home/b3j0f/etc/b3j0fsync-synchronizer.conf
home/b3j0f/etc/b3j0fsync-store.conf
b3j0f.sync-0.0.3.dist-info/METADATA
b3j0f.sync-0.0.3.dist-info/DESCRIPTION.rst
b3j0f.sync-0.0.3.dist-info/RECORD
b3j0f.sync-0.0.3.dist-info/top_level.txt
b3j0f.sync-0.0.3.dist-info/WHEEL
b3j0f.sync-0.0.3.dist-info/metadata.json
