Metadata-Version: 2.0
Name: b3j0f.sync
Version: 0.0.3
Summary: Synchronizer design pattern library
Home-page: https://github.com/b3j0f/sync
Author: b3j0f
Author-email: jlabejof@yahoo.fr
License: MIT License
Keywords: utils,tools,development,synchronizer,design pattern,sync,observer,model,interoperability
Platform: UNKNOWN
Classifier: Development Status :: 3 - Alpha
Classifier: License :: OSI Approved :: MIT License
Classifier: Natural Language :: French
Classifier: Operating System :: OS Independent
Classifier: Topic :: Utilities
Classifier: Topic :: Software Development
Classifier: Intended Audience :: Developers
Classifier: Programming Language :: Python
Classifier: Programming Language :: Python :: 2.6
Classifier: Programming Language :: Python :: 2.7
Classifier: Programming Language :: Python :: 3
Classifier: Programming Language :: Python :: 3.0
Classifier: Programming Language :: Python :: 3.1
Classifier: Programming Language :: Python :: 3.2
Classifier: Programming Language :: Python :: 3.3
Classifier: Programming Language :: Python :: 3.4
Requires-Dist: b3j0f.conf
Requires-Dist: b3j0f.utils
